opmpy/__init__.py
opmpy/_version.py
opmpy/preproc.py
opmpy/coregistration/__init__.py
opmpy/coregistration/anat.py
opmpy/coregistration/opt.py
opmpy/source_imaging/__init__.py
opmpy/source_imaging/lcmv.py
opmpy-0.0.1.dist-info/LICENSE
opmpy-0.0.1.dist-info/METADATA
opmpy-0.0.1.dist-info/WHEEL
opmpy-0.0.1.dist-info/entry_points.txt
opmpy-0.0.1.dist-info/top_level.txt
opmpy-0.0.1.dist-info/RECORD
